ollama_inspect/__init__.py
ollama_inspect/__main__.py
ollama_inspect/gguf_utils.py
ollama_inspect/path_utils.py
ollama_inspect/webapp.py
ollama_inspect/templates/model_metadata.html
ollama_inspect/templates/model_params.html
ollama_inspect/templates/ollama_index.html
ollama_inspect/templates/text_blob.html
ollama_inspect-0.1.1.dist-info/licenses/LICENSE
ollama_inspect-0.1.1.dist-info/METADATA
ollama_inspect-0.1.1.dist-info/WHEEL
ollama_inspect-0.1.1.dist-info/entry_points.txt
ollama_inspect-0.1.1.dist-info/top_level.txt
ollama_inspect-0.1.1.dist-info/RECORD
