Metadata-Version: 2.4
Name: ollama-inspect
Version: 0.1.1
Summary: Ollama Inspect — minimal GGUF inspector web server
Author-email: Bernd Fondermann <python@brainlounge.de>
License: Apache-2.0
Project-URL: Homepage, https://github.com/brainlounge/ollama-inspect
Classifier: Programming Language :: Python :: 3
Classifier: License :: OSI Approved :: Apache Software License
Classifier: Operating System :: OS Independent
Requires-Python: >=3.8
License-File: LICENSE
Requires-Dist: flask>=3.0.0
Requires-Dist: gguf>=0.10.0
Dynamic: license-file
